{
  "database": "Zotero",
  "noteImportFolder": "",
  "pdfExportImageDPI": 120,
  "pdfExportImageFormat": "jpg",
  "pdfExportImageQuality": 90,
  "citeFormats": [
    {
      "name": "Bibliography",
      "format": "formatted-bibliography",
      "cslStyle": "apa"
    }
  ],
  "exportFormats": [
    {
      "name": "Import Zotero Note",
      "outputPathTemplate": "{{citekey}}.md",
      "imageOutputPathTemplate": "{{citekey}}/",
      "imageBaseNameTemplate": "image"
    }
  ],
  "citeSuggestTemplate": "[[{{citekey}}]]",
  "openNoteAfterImport": false,
  "whichNotesToOpenAfterImport": "first-imported-note"
}